setup.cfg
setup.py
topp/__init__.py
topp.build.opencore.egg-info/PKG-INFO
topp.build.opencore.egg-info/SOURCES.txt
topp.build.opencore.egg-info/dependency_links.txt
topp.build.opencore.egg-info/entry_points.txt
topp.build.opencore.egg-info/namespace_packages.txt
topp.build.opencore.egg-info/not-zip-safe
topp.build.opencore.egg-info/requires.txt
topp.build.opencore.egg-info/top_level.txt
topp/build/__init__.py
topp/build/opencore/__init__.py
topp/build/opencore/build.ini
topp/build/opencore/development-requirements.txt
topp/build/opencore/live.ini
topp/build/opencore/local.ini
topp/build/opencore/options.py
topp/build/opencore/production-requirements.txt
topp/build/opencore/results-installed.txt
topp/build/opencore/results-site-created.txt
topp/build/opencore/topp.build.opencore.patch
topp/build/opencore/universal.ini
topp/build/opencore/resources/Products.diff
topp/build/opencore/resources/accontrol.diff
topp/build/opencore/resources/configure.diff
topp/build/opencore/resources/test.py.diff
topp/build/opencore/skel/bin/accept_certificates.sh
topp/build/opencore/skel/bin/create-site.sh
topp/build/opencore/skel/bin/pollzope.sh
topp/build/opencore/skel/zope/README.txt
topp/build/opencore/skel/zope/Extensions/README.txt
topp/build/opencore/skel/zope/Products/README.txt
topp/build/opencore/skel/zope/bin/runzope.bat.in
topp/build/opencore/skel/zope/bin/runzope.in
topp/build/opencore/skel/zope/bin/zopectl.in
topp/build/opencore/skel/zope/bin/zopeservice.py.in
topp/build/opencore/skel/zope/etc/site.zcml
topp/build/opencore/skel/zope/etc/zope.conf.in
topp/build/opencore/skel/zope/import/Examples.zexp
topp/build/opencore/skel/zope/import/README.txt
topp/build/opencore/skel/zope/import/ZopeTutorialExamples.zexp
topp/build/opencore/skel/zope/lib/python/README.txt.in
topp/build/opencore/skel/zope/log/README.txt
topp/build/opencore/skel/zope/var/README.txt
topp/build/opencore/tasks/__init__.py
topp/build/opencore/tasks/opencore.ini
topp/build/opencore/tasks/opencore.py
topp/build/opencore/tasks/pil.ini
topp/build/opencore/tasks/pil.py
topp/build/opencore/tasks/zope.ini
topp/build/opencore/tasks/zope.py
