Metadata-Version: 1.0
Name: topp.build.opencore
Version: 0.5.1
Summary: buildit builder for the opencore softwar
Home-page: UNKNOWN
Author: whit
Author-email: jhammel@openplans.org
License: GPL
Keywords: build topp openplans
Platform: UNKNOWN
